{
    "fluentMethods": true,
    "clientRootFolder": "msstudy",
    "relationships": [],
    "fields": [
        {
            "fieldName": "demofield",
            "fieldType": "String",
            "fieldValidateRules": []
        }
    ],
    "changelogDate": "20190922205106",
    "dto": "no",
    "searchEngine": false,
    "service": "serviceImpl",
    "entityTableName": "demo",
    "databaseType": "sql",
    "jpaMetamodelFiltering": false,
    "pagination": "no",
    "microserviceName": "msstudy"
}
